{
  "timestamp": "2025-11-11T14:33:42.025668",
  "current_power_w": 87761,
  "current_power_kwh": 87.76,
  "daily_total_kwh": 710.88,
  "monthly_total_kwh": 8739.49,
  "lifetime_total_kwh": 1086422.71,
  "daily_environmental": {
    "co2_avoided_kg": 711,
    "trees_planted": 32,
    "households_powered": 0.2,
    "km_driven_equivalent": 2832,
    "km_flown_equivalent": 58,
    "coal_saved_kg": 361,
    "water_saved_litres": 995
  },
  "monthly_environmental": {
    "co2_avoided_kg": 8739,
    "trees_planted": 397,
    "households_powered": 2.46,
    "km_driven_equivalent": 34814,
    "km_flown_equivalent": 712,
    "coal_saved_kg": 4440,
    "water_saved_litres": 12235
  },
  "lifetime_environmental": {
    "co2_avoided_kg": 1086423,
    "trees_planted": 49383,
    "households_powered": 306.33,
    "km_driven_equivalent": 4327808,
    "km_flown_equivalent": 88469,
    "coal_saved_kg": 551928,
    "water_saved_litres": 1520992
  },
  "past_7_days": [
    {
      "date": "2025-11-04",
      "total_kwh": 665.48,
      "environmental": {
        "co2_avoided_kg": 665,
        "trees_planted": 30,
        "households_powered": 0.19,
        "km_driven_equivalent": 2651,
        "km_flown_equivalent": 54,
        "coal_saved_kg": 338,
        "water_saved_litres": 932
      }
    },
    {
      "date": "2025-11-05",
      "total_kwh": 759.99,
      "environmental": {
        "co2_avoided_kg": 760,
        "trees_planted": 35,
        "households_powered": 0.21,
        "km_driven_equivalent": 3027,
        "km_flown_equivalent": 62,
        "coal_saved_kg": 386,
        "water_saved_litres": 1064
      }
    },
    {
      "date": "2025-11-06",
      "total_kwh": 417.06,
      "environmental": {
        "co2_avoided_kg": 417,
        "trees_planted": 19,
        "households_powered": 0.12,
        "km_driven_equivalent": 1661,
        "km_flown_equivalent": 34,
        "coal_saved_kg": 212,
        "water_saved_litres": 584
      }
    },
    {
      "date": "2025-11-07",
      "total_kwh": 863.4,
      "environmental": {
        "co2_avoided_kg": 863,
        "trees_planted": 39,
        "households_powered": 0.24,
        "km_driven_equivalent": 3439,
        "km_flown_equivalent": 70,
        "coal_saved_kg": 439,
        "water_saved_litres": 1209
      }
    },
    {
      "date": "2025-11-08",
      "total_kwh": 1071.64,
      "environmental": {
        "co2_avoided_kg": 1072,
        "trees_planted": 49,
        "households_powered": 0.3,
        "km_driven_equivalent": 4269,
        "km_flown_equivalent": 87,
        "coal_saved_kg": 544,
        "water_saved_litres": 1500
      }
    },
    {
      "date": "2025-11-09",
      "total_kwh": 796.61,
      "environmental": {
        "co2_avoided_kg": 797,
        "trees_planted": 36,
        "households_powered": 0.22,
        "km_driven_equivalent": 3173,
        "km_flown_equivalent": 65,
        "coal_saved_kg": 405,
        "water_saved_litres": 1115
      }
    },
    {
      "date": "2025-11-10",
      "total_kwh": 992.15,
      "environmental": {
        "co2_avoided_kg": 992,
        "trees_planted": 45,
        "households_powered": 0.28,
        "km_driven_equivalent": 3952,
        "km_flown_equivalent": 81,
        "coal_saved_kg": 504,
        "water_saved_litres": 1389
      }
    }
  ],
  "yesterday_total_kwh": 992.15,
  "yesterday_environmental": {
    "co2_avoided_kg": 992,
    "trees_planted": 45,
    "households_powered": 0.28,
    "km_driven_equivalent": 3952,
    "km_flown_equivalent": 81,
    "coal_saved_kg": 504,
    "water_saved_litres": 1389
  }
}