{
  "timestamp": "2026-03-17T11:39:58.835766+00:00",
  "plant_name": "Muir College",
  "location": "Port Elizabeth, South Africa",
  "yesterday_total_kwh": 17.06,
  "daily_total_kwh": 425.86,
  "monthly_total_kwh": 11620.43,
  "lifetime_total_kwh": 1160027.15,
  "yesterday_environmental": {
    "co2_avoided_kg": 17,
    "trees_planted": 1,
    "households_powered": 0.0,
    "km_driven_equivalent": 68,
    "km_flown_equivalent": 1,
    "coal_saved_kg": 9,
    "water_saved_litres": 24
  },
  "daily_environmental": {
    "co2_avoided_kg": 426,
    "trees_planted": 19,
    "households_powered": 0.12,
    "km_driven_equivalent": 1696,
    "km_flown_equivalent": 35,
    "coal_saved_kg": 216,
    "water_saved_litres": 596
  },
  "monthly_environmental": {
    "co2_avoided_kg": 11620,
    "trees_planted": 528,
    "households_powered": 3.28,
    "km_driven_equivalent": 46290,
    "km_flown_equivalent": 946,
    "coal_saved_kg": 5903,
    "water_saved_litres": 16269
  },
  "lifetime_environmental": {
    "co2_avoided_kg": 1160027,
    "trees_planted": 52729,
    "households_powered": 327.08,
    "km_driven_equivalent": 4621015,
    "km_flown_equivalent": 94463,
    "coal_saved_kg": 589321,
    "water_saved_litres": 1624038
  },
  "past_7_days": [
    {
      "date": "2026-03-10",
      "total_kwh": 1003.64,
      "environmental": {
        "co2_avoided_kg": 1004,
        "trees_planted": 46,
        "households_powered": 0.28,
        "km_driven_equivalent": 3998,
        "km_flown_equivalent": 82,
        "coal_saved_kg": 510,
        "water_saved_litres": 1405
      }
    },
    {
      "date": "2026-03-11",
      "total_kwh": 948.33,
      "environmental": {
        "co2_avoided_kg": 948,
        "trees_planted": 43,
        "households_powered": 0.27,
        "km_driven_equivalent": 3778,
        "km_flown_equivalent": 77,
        "coal_saved_kg": 482,
        "water_saved_litres": 1328
      }
    },
    {
      "date": "2026-03-12",
      "total_kwh": 929.15,
      "environmental": {
        "co2_avoided_kg": 929,
        "trees_planted": 42,
        "households_powered": 0.26,
        "km_driven_equivalent": 3701,
        "km_flown_equivalent": 76,
        "coal_saved_kg": 472,
        "water_saved_litres": 1301
      }
    },
    {
      "date": "2026-03-13",
      "total_kwh": 938.99,
      "environmental": {
        "co2_avoided_kg": 939,
        "trees_planted": 43,
        "households_powered": 0.26,
        "km_driven_equivalent": 3740,
        "km_flown_equivalent": 76,
        "coal_saved_kg": 477,
        "water_saved_litres": 1315
      }
    },
    {
      "date": "2026-03-14",
      "total_kwh": 506.18,
      "environmental": {
        "co2_avoided_kg": 506,
        "trees_planted": 23,
        "households_powered": 0.14,
        "km_driven_equivalent": 2016,
        "km_flown_equivalent": 41,
        "coal_saved_kg": 257,
        "water_saved_litres": 709
      }
    },
    {
      "date": "2026-03-15",
      "total_kwh": 7.39,
      "environmental": {
        "co2_avoided_kg": 7,
        "trees_planted": 0,
        "households_powered": 0.0,
        "km_driven_equivalent": 29,
        "km_flown_equivalent": 1,
        "coal_saved_kg": 4,
        "water_saved_litres": 10
      }
    },
    {
      "date": "2026-03-16",
      "total_kwh": 17.06,
      "environmental": {
        "co2_avoided_kg": 17,
        "trees_planted": 1,
        "households_powered": 0.0,
        "km_driven_equivalent": 68,
        "km_flown_equivalent": 1,
        "coal_saved_kg": 9,
        "water_saved_litres": 24
      }
    }
  ]
}