{
  "timestamp": "2026-05-28T10:14:04.903155+00:00",
  "plant_name": "Muir College",
  "location": "Port Elizabeth, South Africa",
  "yesterday_total_kwh": 677.21,
  "daily_total_kwh": 280.43,
  "monthly_total_kwh": 13897.55,
  "lifetime_total_kwh": 1199996.91,
  "yesterday_environmental": {
    "co2_avoided_kg": 677,
    "trees_planted": 31,
    "households_powered": 0.19,
    "km_driven_equivalent": 2698,
    "km_flown_equivalent": 55,
    "coal_saved_kg": 344,
    "water_saved_litres": 948
  },
  "daily_environmental": {
    "co2_avoided_kg": 280,
    "trees_planted": 13,
    "households_powered": 0.08,
    "km_driven_equivalent": 1117,
    "km_flown_equivalent": 23,
    "coal_saved_kg": 142,
    "water_saved_litres": 393
  },
  "monthly_environmental": {
    "co2_avoided_kg": 13898,
    "trees_planted": 632,
    "households_powered": 3.92,
    "km_driven_equivalent": 55361,
    "km_flown_equivalent": 1132,
    "coal_saved_kg": 7060,
    "water_saved_litres": 19457
  },
  "lifetime_environmental": {
    "co2_avoided_kg": 1199997,
    "trees_planted": 54545,
    "households_powered": 338.35,
    "km_driven_equivalent": 4780236,
    "km_flown_equivalent": 97718,
    "coal_saved_kg": 609626,
    "water_saved_litres": 1679996
  },
  "past_7_days": [
    {
      "date": "2026-05-21",
      "total_kwh": 147.07,
      "environmental": {
        "co2_avoided_kg": 147,
        "trees_planted": 7,
        "households_powered": 0.04,
        "km_driven_equivalent": 586,
        "km_flown_equivalent": 12,
        "coal_saved_kg": 75,
        "water_saved_litres": 206
      }
    },
    {
      "date": "2026-05-22",
      "total_kwh": 547.77,
      "environmental": {
        "co2_avoided_kg": 548,
        "trees_planted": 25,
        "households_powered": 0.15,
        "km_driven_equivalent": 2182,
        "km_flown_equivalent": 45,
        "coal_saved_kg": 278,
        "water_saved_litres": 767
      }
    },
    {
      "date": "2026-05-23",
      "total_kwh": 529.54,
      "environmental": {
        "co2_avoided_kg": 530,
        "trees_planted": 24,
        "households_powered": 0.15,
        "km_driven_equivalent": 2109,
        "km_flown_equivalent": 43,
        "coal_saved_kg": 269,
        "water_saved_litres": 741
      }
    },
    {
      "date": "2026-05-24",
      "total_kwh": 670.48,
      "environmental": {
        "co2_avoided_kg": 670,
        "trees_planted": 30,
        "households_powered": 0.19,
        "km_driven_equivalent": 2671,
        "km_flown_equivalent": 55,
        "coal_saved_kg": 341,
        "water_saved_litres": 939
      }
    },
    {
      "date": "2026-05-25",
      "total_kwh": 627.61,
      "environmental": {
        "co2_avoided_kg": 628,
        "trees_planted": 29,
        "households_powered": 0.18,
        "km_driven_equivalent": 2500,
        "km_flown_equivalent": 51,
        "coal_saved_kg": 319,
        "water_saved_litres": 879
      }
    },
    {
      "date": "2026-05-26",
      "total_kwh": 664.87,
      "environmental": {
        "co2_avoided_kg": 665,
        "trees_planted": 30,
        "households_powered": 0.19,
        "km_driven_equivalent": 2649,
        "km_flown_equivalent": 54,
        "coal_saved_kg": 338,
        "water_saved_litres": 931
      }
    },
    {
      "date": "2026-05-27",
      "total_kwh": 677.21,
      "environmental": {
        "co2_avoided_kg": 677,
        "trees_planted": 31,
        "households_powered": 0.19,
        "km_driven_equivalent": 2698,
        "km_flown_equivalent": 55,
        "coal_saved_kg": 344,
        "water_saved_litres": 948
      }
    }
  ]
}