{
  "lifetime_total_kwh": 1145395.0718333335,
  "month_start_total_kwh": 13717.492749999998,
  "current_month": 2,
  "current_year": 2026,
  "last_daily_total": 149.80991666666668,
  "last_update_date": "2026-02-24",
  "daily_history": [
    {
      "date": "2026-02-17",
      "total_kwh": 755.36,
      "environmental": {
        "co2_avoided_kg": 755,
        "trees_planted": 34,
        "households_powered": 0.21,
        "km_driven_equivalent": 3009,
        "km_flown_equivalent": 62,
        "coal_saved_kg": 384,
        "water_saved_litres": 1058
      }
    },
    {
      "date": "2026-02-18",
      "total_kwh": 834.58,
      "environmental": {
        "co2_avoided_kg": 835,
        "trees_planted": 38,
        "households_powered": 0.24,
        "km_driven_equivalent": 3325,
        "km_flown_equivalent": 68,
        "coal_saved_kg": 424,
        "water_saved_litres": 1168
      }
    },
    {
      "date": "2026-02-19",
      "total_kwh": 995.42,
      "environmental": {
        "co2_avoided_kg": 995,
        "trees_planted": 45,
        "households_powered": 0.28,
        "km_driven_equivalent": 3965,
        "km_flown_equivalent": 81,
        "coal_saved_kg": 506,
        "water_saved_litres": 1394
      }
    },
    {
      "date": "2026-02-20",
      "total_kwh": 196.54,
      "environmental": {
        "co2_avoided_kg": 197,
        "trees_planted": 9,
        "households_powered": 0.06,
        "km_driven_equivalent": 783,
        "km_flown_equivalent": 16,
        "coal_saved_kg": 100,
        "water_saved_litres": 275
      }
    },
    {
      "date": "2026-02-21",
      "total_kwh": 362.72,
      "environmental": {
        "co2_avoided_kg": 363,
        "trees_planted": 16,
        "households_powered": 0.1,
        "km_driven_equivalent": 1445,
        "km_flown_equivalent": 30,
        "coal_saved_kg": 184,
        "water_saved_litres": 508
      }
    },
    {
      "date": "2026-02-22",
      "total_kwh": 979.9,
      "environmental": {
        "co2_avoided_kg": 980,
        "trees_planted": 45,
        "households_powered": 0.28,
        "km_driven_equivalent": 3903,
        "km_flown_equivalent": 80,
        "coal_saved_kg": 498,
        "water_saved_litres": 1372
      }
    },
    {
      "date": "2026-02-23",
      "total_kwh": 292.53,
      "environmental": {
        "co2_avoided_kg": 293,
        "trees_planted": 13,
        "households_powered": 0.08,
        "km_driven_equivalent": 1165,
        "km_flown_equivalent": 24,
        "coal_saved_kg": 149,
        "water_saved_litres": 410
      }
    }
  ]
}