{
  "lifetime_total_kwh": 1169505.8236666657,
  "month_start_total_kwh": 1895.7529999999995,
  "current_month": 4,
  "current_year": 2026,
  "last_daily_total": 582.0302499999999,
  "last_update_date": "2026-04-04",
  "daily_history": [
    {
      "date": "2026-03-28",
      "total_kwh": 808.97,
      "environmental": {
        "co2_avoided_kg": 809,
        "trees_planted": 37,
        "households_powered": 0.23,
        "km_driven_equivalent": 3223,
        "km_flown_equivalent": 66,
        "coal_saved_kg": 411,
        "water_saved_litres": 1133
      }
    },
    {
      "date": "2026-03-29",
      "total_kwh": 929.71,
      "environmental": {
        "co2_avoided_kg": 930,
        "trees_planted": 42,
        "households_powered": 0.26,
        "km_driven_equivalent": 3704,
        "km_flown_equivalent": 76,
        "coal_saved_kg": 472,
        "water_saved_litres": 1302
      }
    },
    {
      "date": "2026-03-30",
      "total_kwh": 245.44,
      "environmental": {
        "co2_avoided_kg": 245,
        "trees_planted": 11,
        "households_powered": 0.07,
        "km_driven_equivalent": 978,
        "km_flown_equivalent": 20,
        "coal_saved_kg": 125,
        "water_saved_litres": 344
      }
    },
    {
      "date": "2026-03-31",
      "total_kwh": 672.66,
      "environmental": {
        "co2_avoided_kg": 673,
        "trees_planted": 31,
        "households_powered": 0.19,
        "km_driven_equivalent": 2680,
        "km_flown_equivalent": 55,
        "coal_saved_kg": 342,
        "water_saved_litres": 942
      }
    },
    {
      "date": "2026-04-01",
      "total_kwh": 886.99,
      "environmental": {
        "co2_avoided_kg": 887,
        "trees_planted": 40,
        "households_powered": 0.25,
        "km_driven_equivalent": 3533,
        "km_flown_equivalent": 72,
        "coal_saved_kg": 451,
        "water_saved_litres": 1242
      }
    },
    {
      "date": "2026-04-02",
      "total_kwh": 536.47,
      "environmental": {
        "co2_avoided_kg": 536,
        "trees_planted": 24,
        "households_powered": 0.15,
        "km_driven_equivalent": 2137,
        "km_flown_equivalent": 44,
        "coal_saved_kg": 273,
        "water_saved_litres": 751
      }
    },
    {
      "date": "2026-04-03",
      "total_kwh": 472.29,
      "environmental": {
        "co2_avoided_kg": 472,
        "trees_planted": 21,
        "households_powered": 0.13,
        "km_driven_equivalent": 1881,
        "km_flown_equivalent": 38,
        "coal_saved_kg": 240,
        "water_saved_litres": 661
      }
    }
  ]
}